{"sections":{"main":{"type":"cart-template","settings":{}},"recent-viewed-products":{"type":"recent-viewed-products","settings":{"container":"container","color_scheme":"","heading":"Recently Viewed Products","heading_size":"h3","text_align":"left","limit":8,"columns":4,"column_gap":30,"pcard_layout":"","pcard_image_ratio":"","show_vendor":false,"hide_title":false,"enable_slider":true,"show_pagination":false,"show_navigation":false,"mobile_disable_slider":false,"use_scroll_mobile":true,"item_gap_mobile":16,"padding_top":0,"padding_bottom":0,"custom_class":"","animations":"inherit"}},"wsp_whatsapp_exB3ty":{"type":"wsp_whatsapp","settings":{"show_whatsapp":true,"whatsapp_number":"+91 8178772995","whatsapp_msg":"I Want To Order : Will You Send The Edited Image To Customer Before Printing"}}},"order":["main","recent-viewed-products","wsp_whatsapp_exB3ty"]}